[
  {
    "code": "RH01",
    "name": "Standard Red",
    "hex": "#A5362F",
    "R": 165,
    "G": 54,
    "B": 47,
    "L": 39.4,
    "a": 58.5,
    "b": 29.0
  },
  {
    "code": "RH02",
    "name": "Bright Red",
    "hex": "#E21F2F",
    "R": 226,
    "G": 31,
    "B": 47,
    "L": 47.4,
    "a": 70.1,
    "b": 44.0
  },
  {
    "code": "RH10",
    "name": "Standard Green",
    "hex": "#609B63",
    "R": 96,
    "G": 155,
    "B": 99,
    "L": 40.5,
    "a": -42.2,
    "b": 17.9
  },
  {
    "code": "RH11",
    "name": "Bright Green",
    "hex": "#3BB44A",
    "R": 59,
    "G": 180,
    "B": 74,
    "L": 62.1,
    "a": -47.7,
    "b": 47.2
  },
  {
    "code": "RH12",
    "name": "Dark Green",
    "hex": "#006C55",
    "R": 0,
    "G": 108,
    "B": 85,
    "L": 39.6,
    "a": -38.3,
    "b": 13.1
  },
  {
    "code": "RH20",
    "name": "Standard Blue",
    "hex": "#0075BC",
    "R": 0,
    "G": 117,
    "B": 188,
    "L": 36.4,
    "a": 14.2,
    "b": -46.7
  },
  {
    "code": "RH21",
    "name": "Purple",
    "hex": "#493D8C",
    "R": 73,
    "G": 61,
    "B": 140,
    "L": 31.5,
    "a": 41.9,
    "b": -40.9
  },
  {
    "code": "RH22",
    "name": "Light Blue",
    "hex": "#47AFE3",
    "R": 71,
    "G": 175,
    "B": 227,
    "L": 55.3,
    "a": -19.1,
    "b": -37.3
  },
  {
    "code": "RH23",
    "name": "Azure",
    "hex": "#039DC4",
    "R": 3,
    "G": 157,
    "B": 196,
    "L": 47.7,
    "a": -4.8,
    "b": -34.8
  },
  {
    "code": "RH26",
    "name": "Turquoise",
    "hex": "#00A6A3",
    "R": 0,
    "G": 166,
    "B": 163,
    "L": 58.8,
    "a": -38.4,
    "b": -3.0
  },
  {
    "code": "RH30",
    "name": "Standard Beige",
    "hex": "#E4C4AA",
    "R": 228,
    "G": 196,
    "B": 170,
    "L": 75.2,
    "a": 3.8,
    "b": 24.8
  },
  {
    "code": "RH31",
    "name": "Cream",
    "hex": "#E8E3D8",
    "R": 232,
    "G": 227,
    "B": 216,
    "L": 91.8,
    "a": -0.5,
    "b": 12.5
  },
  {
    "code": "RH32",
    "name": "Brown",
    "hex": "#8B5F3C",
    "R": 139,
    "G": 95,
    "B": 60,
    "L": 40.0,
    "a": 15.9,
    "b": 27.1
  },
  {
    "code": "RH90",
    "name": "Funky Pink",
    "hex": "#E8457E",
    "R": 232,
    "G": 69,
    "B": 126,
    "L": 55.0,
    "a": 66.1,
    "b": 4.9
  },
  {
    "code": "RH40",
    "name": "Mustard Yellow",
    "hex": "#E5A144",
    "R": 229,
    "G": 161,
    "B": 68,
    "L": 66.0,
    "a": 8.4,
    "b": 56.3
  },
  {
    "code": "RH41",
    "name": "Bright Yellow",
    "hex": "#FFD833",
    "R": 255,
    "G": 216,
    "B": 51,
    "L": 86.9,
    "a": -1.0,
    "b": 90.6
  },
  {
    "code": "RH50",
    "name": "Orange",
    "hex": "#F15B32",
    "R": 241,
    "G": 91,
    "B": 50,
    "L": 63.2,
    "a": 49.8,
    "b": 60.2
  },
  {
    "code": "RH60",
    "name": "Dark Grey",
    "hex": "#59595B",
    "R": 89,
    "G": 89,
    "B": 91,
    "L": 34.1,
    "a": -0.4,
    "b": -2.4
  },
  {
    "code": "RH61",
    "name": "Light Grey",
    "hex": "#939598",
    "R": 147,
    "G": 149,
    "B": 152,
    "L": 69.0,
    "a": -0.5,
    "b": -1.0
  },
  {
    "code": "RH65",
    "name": "Pale Grey",
    "hex": "#D9D9D6",
    "R": 217,
    "G": 217,
    "B": 214,
    "L": 87.6,
    "a": -0.2,
    "b": -0.7
  },
  {
    "code": "RH70",
    "name": "Black",
    "hex": "#231F20",
    "R": 35,
    "G": 31,
    "B": 32,
    "L": 9.1,
    "a": -0.3,
    "b": -6.3
  }
]